{"city":"delhi","name":"Delhi","generated_at":"2026-04-28T18:45:56.145Z","source":{"weather":"open-meteo","aqi":"open-meteo-air-quality"},"points_24h":[{"t":"2026-04-27T19:00Z","temp":31.5,"humidity":32,"aqi":529},{"t":"2026-04-27T20:00Z","temp":31,"humidity":33,"aqi":535},{"t":"2026-04-27T21:00Z","temp":30.5,"humidity":35,"aqi":542},{"t":"2026-04-27T22:00Z","temp":30.3,"humidity":35,"aqi":548},{"t":"2026-04-27T23:00Z","temp":30.5,"humidity":33,"aqi":554},{"t":"2026-04-28T00:00Z","temp":29.6,"humidity":39,"aqi":557},{"t":"2026-04-28T01:00Z","temp":30,"humidity":39,"aqi":572},{"t":"2026-04-28T02:00Z","temp":30.7,"humidity":38,"aqi":590},{"t":"2026-04-28T03:00Z","temp":32.5,"humidity":35,"aqi":614},{"t":"2026-04-28T04:00Z","temp":34.5,"humidity":31,"aqi":644},{"t":"2026-04-28T05:00Z","temp":36.4,"humidity":26,"aqi":675},{"t":"2026-04-28T06:00Z","temp":37,"humidity":25,"aqi":701},{"t":"2026-04-28T07:00Z","temp":36,"humidity":27,"aqi":721},{"t":"2026-04-28T08:00Z","temp":36.6,"humidity":26,"aqi":734},{"t":"2026-04-28T09:00Z","temp":37,"humidity":24,"aqi":742},{"t":"2026-04-28T10:00Z","temp":36.4,"humidity":24,"aqi":746},{"t":"2026-04-28T11:00Z","temp":35.3,"humidity":26,"aqi":747},{"t":"2026-04-28T12:00Z","temp":35,"humidity":27,"aqi":746},{"t":"2026-04-28T13:00Z","temp":34.3,"humidity":29,"aqi":728},{"t":"2026-04-28T14:00Z","temp":33.2,"humidity":32,"aqi":698},{"t":"2026-04-28T15:00Z","temp":32.4,"humidity":36,"aqi":659},{"t":"2026-04-28T16:00Z","temp":31.7,"humidity":40,"aqi":612},{"t":"2026-04-28T17:00Z","temp":31,"humidity":40,"aqi":566},{"t":"2026-04-28T18:00Z","temp":30.5,"humidity":47,"aqi":525},{"t":"2026-04-28T18:45:56.145Z","temp":30.2,"humidity":48,"aqi":566}],"points_7d":[{"t":"2026-04-21T19:00Z","temp":29.4,"humidity":28,"aqi":450},{"t":"2026-04-21T20:00Z","temp":28.5,"humidity":31,"aqi":451},{"t":"2026-04-21T21:00Z","temp":28.2,"humidity":30,"aqi":453},{"t":"2026-04-21T22:00Z","temp":27.9,"humidity":31,"aqi":454},{"t":"2026-04-21T23:00Z","temp":27.1,"humidity":30,"aqi":452},{"t":"2026-04-22T00:00Z","temp":26,"humidity":36,"aqi":449},{"t":"2026-04-22T01:00Z","temp":26,"humidity":36,"aqi":450},{"t":"2026-04-22T02:00Z","temp":27.5,"humidity":34,"aqi":451},{"t":"2026-04-22T03:00Z","temp":30,"humidity":29,"aqi":454},{"t":"2026-04-22T04:00Z","temp":33.7,"humidity":21,"aqi":456},{"t":"2026-04-22T05:00Z","temp":36.4,"humidity":17,"aqi":456},{"t":"2026-04-22T06:00Z","temp":38,"humidity":14,"aqi":453},{"t":"2026-04-22T07:00Z","temp":39.4,"humidity":12,"aqi":449},{"t":"2026-04-22T08:00Z","temp":40,"humidity":11,"aqi":446},{"t":"2026-04-22T09:00Z","temp":40.3,"humidity":11,"aqi":443},{"t":"2026-04-22T10:00Z","temp":40.3,"humidity":11,"aqi":439},{"t":"2026-04-22T11:00Z","temp":39.8,"humidity":11,"aqi":435},{"t":"2026-04-22T12:00Z","temp":39.5,"humidity":12,"aqi":429},{"t":"2026-04-22T13:00Z","temp":38,"humidity":13,"aqi":425},{"t":"2026-04-22T14:00Z","temp":36.2,"humidity":15,"aqi":420},{"t":"2026-04-22T15:00Z","temp":34.7,"humidity":17,"aqi":415},{"t":"2026-04-22T16:00Z","temp":33.8,"humidity":18,"aqi":409},{"t":"2026-04-22T17:00Z","temp":32,"humidity":21,"aqi":404},{"t":"2026-04-22T18:00Z","temp":31.5,"humidity":22,"aqi":397},{"t":"2026-04-22T19:00Z","temp":30.1,"humidity":25,"aqi":390},{"t":"2026-04-22T20:00Z","temp":29.1,"humidity":26,"aqi":383},{"t":"2026-04-22T21:00Z","temp":28.4,"humidity":27,"aqi":372},{"t":"2026-04-22T22:00Z","temp":27.9,"humidity":27,"aqi":364},{"t":"2026-04-22T23:00Z","temp":28,"humidity":25,"aqi":362},{"t":"2026-04-23T00:00Z","temp":28.1,"humidity":22,"aqi":363},{"t":"2026-04-23T01:00Z","temp":28.3,"humidity":20,"aqi":358},{"t":"2026-04-23T02:00Z","temp":29.5,"humidity":18,"aqi":355},{"t":"2026-04-23T03:00Z","temp":31.6,"humidity":16,"aqi":353},{"t":"2026-04-23T04:00Z","temp":34,"humidity":15,"aqi":352},{"t":"2026-04-23T05:00Z","temp":36.5,"humidity":14,"aqi":355},{"t":"2026-04-23T06:00Z","temp":38.5,"humidity":13,"aqi":360},{"t":"2026-04-23T07:00Z","temp":40,"humidity":12,"aqi":363},{"t":"2026-04-23T08:00Z","temp":40.8,"humidity":11,"aqi":361},{"t":"2026-04-23T09:00Z","temp":41.2,"humidity":11,"aqi":353},{"t":"2026-04-23T10:00Z","temp":41,"humidity":11,"aqi":341},{"t":"2026-04-23T11:00Z","temp":40.3,"humidity":11,"aqi":325},{"t":"2026-04-23T12:00Z","temp":39.4,"humidity":12,"aqi":310},{"t":"2026-04-23T13:00Z","temp":38.3,"humidity":14,"aqi":297},{"t":"2026-04-23T14:00Z","temp":36.8,"humidity":16,"aqi":283},{"t":"2026-04-23T15:00Z","temp":35,"humidity":18,"aqi":269},{"t":"2026-04-23T16:00Z","temp":33.5,"humidity":21,"aqi":253},{"t":"2026-04-23T17:00Z","temp":32.5,"humidity":21,"aqi":233},{"t":"2026-04-23T18:00Z","temp":31.5,"humidity":26,"aqi":211},{"t":"2026-04-23T19:00Z","temp":30.3,"humidity":27,"aqi":195},{"t":"2026-04-23T20:00Z","temp":29.1,"humidity":33,"aqi":188},{"t":"2026-04-23T21:00Z","temp":29.2,"humidity":29,"aqi":182},{"t":"2026-04-23T22:00Z","temp":28.5,"humidity":30,"aqi":177},{"t":"2026-04-23T23:00Z","temp":28.2,"humidity":30,"aqi":171},{"t":"2026-04-24T00:00Z","temp":27.5,"humidity":39,"aqi":167},{"t":"2026-04-24T01:00Z","temp":28.4,"humidity":31,"aqi":165},{"t":"2026-04-24T02:00Z","temp":29.7,"humidity":29,"aqi":163},{"t":"2026-04-24T03:00Z","temp":31.9,"humidity":27,"aqi":160},{"t":"2026-04-24T04:00Z","temp":34.9,"humidity":24,"aqi":157},{"t":"2026-04-24T05:00Z","temp":37.7,"humidity":20,"aqi":154},{"t":"2026-04-24T06:00Z","temp":39.6,"humidity":16,"aqi":151},{"t":"2026-04-24T07:00Z","temp":41.4,"humidity":13,"aqi":150},{"t":"2026-04-24T08:00Z","temp":42,"humidity":13,"aqi":150},{"t":"2026-04-24T09:00Z","temp":41.6,"humidity":13,"aqi":150},{"t":"2026-04-24T10:00Z","temp":41.7,"humidity":13,"aqi":150},{"t":"2026-04-24T11:00Z","temp":41.2,"humidity":13,"aqi":154},{"t":"2026-04-24T12:00Z","temp":41.1,"humidity":10,"aqi":163},{"t":"2026-04-24T13:00Z","temp":39.5,"humidity":12,"aqi":164},{"t":"2026-04-24T14:00Z","temp":36.6,"humidity":21,"aqi":153},{"t":"2026-04-24T15:00Z","temp":36,"humidity":23,"aqi":153},{"t":"2026-04-24T16:00Z","temp":34.3,"humidity":25,"aqi":156},{"t":"2026-04-24T17:00Z","temp":33.5,"humidity":21,"aqi":160},{"t":"2026-04-24T18:00Z","temp":32.5,"humidity":29,"aqi":166},{"t":"2026-04-24T19:00Z","temp":31.8,"humidity":32,"aqi":174},{"t":"2026-04-24T20:00Z","temp":31,"humidity":30,"aqi":181},{"t":"2026-04-24T21:00Z","temp":30.1,"humidity":29,"aqi":189},{"t":"2026-04-24T22:00Z","temp":29.5,"humidity":31,"aqi":197},{"t":"2026-04-24T23:00Z","temp":29.1,"humidity":33,"aqi":224},{"t":"2026-04-25T00:00Z","temp":29,"humidity":41,"aqi":258},{"t":"2026-04-25T01:00Z","temp":29.9,"humidity":37,"aqi":272},{"t":"2026-04-25T02:00Z","temp":31,"humidity":33,"aqi":289},{"t":"2026-04-25T03:00Z","temp":32.9,"humidity":30,"aqi":306},{"t":"2026-04-25T04:00Z","temp":35.8,"humidity":25,"aqi":321},{"t":"2026-04-25T05:00Z","temp":38.9,"humidity":20,"aqi":336},{"t":"2026-04-25T06:00Z","temp":40.8,"humidity":14,"aqi":346},{"t":"2026-04-25T07:00Z","temp":41.8,"humidity":13,"aqi":359},{"t":"2026-04-25T08:00Z","temp":42.2,"humidity":12,"aqi":373},{"t":"2026-04-25T09:00Z","temp":42,"humidity":13,"aqi":388},{"t":"2026-04-25T10:00Z","temp":41.7,"humidity":12,"aqi":403},{"t":"2026-04-25T11:00Z","temp":41.5,"humidity":13,"aqi":417},{"t":"2026-04-25T12:00Z","temp":41.1,"humidity":13,"aqi":439},{"t":"2026-04-25T13:00Z","temp":39.4,"humidity":14,"aqi":454},{"t":"2026-04-25T14:00Z","temp":37.8,"humidity":16,"aqi":477},{"t":"2026-04-25T15:00Z","temp":36.6,"humidity":17,"aqi":508},{"t":"2026-04-25T16:00Z","temp":35.1,"humidity":19,"aqi":538},{"t":"2026-04-25T17:00Z","temp":33.7,"humidity":22,"aqi":559},{"t":"2026-04-25T18:00Z","temp":33.2,"humidity":25,"aqi":571},{"t":"2026-04-25T19:00Z","temp":32.7,"humidity":26,"aqi":576},{"t":"2026-04-25T20:00Z","temp":31.9,"humidity":29,"aqi":578},{"t":"2026-04-25T21:00Z","temp":31.1,"humidity":31,"aqi":579},{"t":"2026-04-25T22:00Z","temp":30.4,"humidity":32,"aqi":575},{"t":"2026-04-25T23:00Z","temp":29.5,"humidity":33,"aqi":563},{"t":"2026-04-26T00:00Z","temp":28.8,"humidity":38,"aqi":549},{"t":"2026-04-26T01:00Z","temp":29.3,"humidity":36,"aqi":556},{"t":"2026-04-26T02:00Z","temp":30.5,"humidity":34,"aqi":560},{"t":"2026-04-26T03:00Z","temp":33.2,"humidity":30,"aqi":564},{"t":"2026-04-26T04:00Z","temp":36,"humidity":26,"aqi":568},{"t":"2026-04-26T05:00Z","temp":38.3,"humidity":21,"aqi":568},{"t":"2026-04-26T06:00Z","temp":40,"humidity":19,"aqi":565},{"t":"2026-04-26T07:00Z","temp":41,"humidity":17,"aqi":565},{"t":"2026-04-26T08:00Z","temp":41.5,"humidity":16,"aqi":568},{"t":"2026-04-26T09:00Z","temp":41.2,"humidity":15,"aqi":573},{"t":"2026-04-26T10:00Z","temp":40,"humidity":16,"aqi":578},{"t":"2026-04-26T11:00Z","temp":39.5,"humidity":17,"aqi":582},{"t":"2026-04-26T12:00Z","temp":40.5,"humidity":15,"aqi":579},{"t":"2026-04-26T13:00Z","temp":39.2,"humidity":16,"aqi":581},{"t":"2026-04-26T14:00Z","temp":37.5,"humidity":17,"aqi":575},{"t":"2026-04-26T15:00Z","temp":36.5,"humidity":18,"aqi":561},{"t":"2026-04-26T16:00Z","temp":35.3,"humidity":19,"aqi":551},{"t":"2026-04-26T17:00Z","temp":34.5,"humidity":20,"aqi":548},{"t":"2026-04-26T18:00Z","temp":33.4,"humidity":23,"aqi":553},{"t":"2026-04-26T19:00Z","temp":31.7,"humidity":26,"aqi":560},{"t":"2026-04-26T20:00Z","temp":30.7,"humidity":33,"aqi":565},{"t":"2026-04-26T21:00Z","temp":30,"humidity":33,"aqi":567},{"t":"2026-04-26T22:00Z","temp":29.2,"humidity":33,"aqi":569},{"t":"2026-04-26T23:00Z","temp":28.5,"humidity":36,"aqi":571},{"t":"2026-04-27T00:00Z","temp":29,"humidity":36,"aqi":574},{"t":"2026-04-27T01:00Z","temp":29.9,"humidity":31,"aqi":568},{"t":"2026-04-27T02:00Z","temp":31.6,"humidity":27,"aqi":562},{"t":"2026-04-27T03:00Z","temp":34.1,"humidity":23,"aqi":556},{"t":"2026-04-27T04:00Z","temp":36.6,"humidity":19,"aqi":549},{"t":"2026-04-27T05:00Z","temp":38.8,"humidity":15,"aqi":540},{"t":"2026-04-27T06:00Z","temp":39.8,"humidity":15,"aqi":532},{"t":"2026-04-27T07:00Z","temp":41.3,"humidity":14,"aqi":520},{"t":"2026-04-27T08:00Z","temp":42.1,"humidity":14,"aqi":507},{"t":"2026-04-27T09:00Z","temp":42.2,"humidity":14,"aqi":492},{"t":"2026-04-27T10:00Z","temp":41.8,"humidity":14,"aqi":478},{"t":"2026-04-27T11:00Z","temp":41.2,"humidity":13,"aqi":466},{"t":"2026-04-27T12:00Z","temp":40.6,"humidity":12,"aqi":455},{"t":"2026-04-27T13:00Z","temp":39.5,"humidity":13,"aqi":458},{"t":"2026-04-27T14:00Z","temp":38.3,"humidity":14,"aqi":467},{"t":"2026-04-27T15:00Z","temp":38,"humidity":14,"aqi":483},{"t":"2026-04-27T16:00Z","temp":33.6,"humidity":26,"aqi":502},{"t":"2026-04-27T17:00Z","temp":33.2,"humidity":27,"aqi":516},{"t":"2026-04-27T18:00Z","temp":32.5,"humidity":28,"aqi":524},{"t":"2026-04-27T19:00Z","temp":31.5,"humidity":32,"aqi":529},{"t":"2026-04-27T20:00Z","temp":31,"humidity":33,"aqi":535},{"t":"2026-04-27T21:00Z","temp":30.5,"humidity":35,"aqi":542},{"t":"2026-04-27T22:00Z","temp":30.3,"humidity":35,"aqi":548},{"t":"2026-04-27T23:00Z","temp":30.5,"humidity":33,"aqi":554},{"t":"2026-04-28T00:00Z","temp":29.6,"humidity":39,"aqi":557},{"t":"2026-04-28T01:00Z","temp":30,"humidity":39,"aqi":572},{"t":"2026-04-28T02:00Z","temp":30.7,"humidity":38,"aqi":590},{"t":"2026-04-28T03:00Z","temp":32.5,"humidity":35,"aqi":614},{"t":"2026-04-28T04:00Z","temp":34.5,"humidity":31,"aqi":644},{"t":"2026-04-28T05:00Z","temp":36.4,"humidity":26,"aqi":675},{"t":"2026-04-28T06:00Z","temp":37,"humidity":25,"aqi":701},{"t":"2026-04-28T07:00Z","temp":36,"humidity":27,"aqi":721},{"t":"2026-04-28T08:00Z","temp":36.6,"humidity":26,"aqi":734},{"t":"2026-04-28T09:00Z","temp":37,"humidity":24,"aqi":742},{"t":"2026-04-28T10:00Z","temp":36.4,"humidity":24,"aqi":746},{"t":"2026-04-28T11:00Z","temp":35.3,"humidity":26,"aqi":747},{"t":"2026-04-28T12:00Z","temp":35,"humidity":27,"aqi":746},{"t":"2026-04-28T13:00Z","temp":34.3,"humidity":29,"aqi":728},{"t":"2026-04-28T14:00Z","temp":33.2,"humidity":32,"aqi":698},{"t":"2026-04-28T15:00Z","temp":32.4,"humidity":36,"aqi":659},{"t":"2026-04-28T16:00Z","temp":31.7,"humidity":40,"aqi":612},{"t":"2026-04-28T17:00Z","temp":31,"humidity":40,"aqi":566},{"t":"2026-04-28T18:00Z","temp":30.5,"humidity":47,"aqi":525}],"points_30d":[{"t":"2026-03-30T00:00:00.000Z","temp":25.7,"humidity":56.3,"aqi":242.7},{"t":"2026-03-30T06:00:00.000Z","temp":31.7,"humidity":29.7,"aqi":248.3},{"t":"2026-03-30T12:00:00.000Z","temp":26.2,"humidity":52,"aqi":245.7},{"t":"2026-03-30T18:00:00.000Z","temp":22.9,"humidity":71.3,"aqi":211.8},{"t":"2026-03-31T00:00:00.000Z","temp":25.6,"humidity":55.5,"aqi":178.3},{"t":"2026-03-31T06:00:00.000Z","temp":32.2,"humidity":25.7,"aqi":148.7},{"t":"2026-03-31T12:00:00.000Z","temp":24.1,"humidity":62.5,"aqi":130.2},{"t":"2026-03-31T18:00:00.000Z","temp":21.6,"humidity":70.7,"aqi":126.3},{"t":"2026-04-01T00:00:00.000Z","temp":23.5,"humidity":62.7,"aqi":130},{"t":"2026-04-01T06:00:00.000Z","temp":32,"humidity":28.3,"aqi":146},{"t":"2026-04-01T12:00:00.000Z","temp":28.2,"humidity":43.3,"aqi":151},{"t":"2026-04-01T18:00:00.000Z","temp":23.9,"humidity":65.3,"aqi":150.8},{"t":"2026-04-02T00:00:00.000Z","temp":25.7,"humidity":56.8,"aqi":144.7},{"t":"2026-04-02T06:00:00.000Z","temp":33.2,"humidity":28.3,"aqi":128.3},{"t":"2026-04-02T12:00:00.000Z","temp":30.5,"humidity":39,"aqi":133.8},{"t":"2026-04-02T18:00:00.000Z","temp":25.2,"humidity":59.2,"aqi":129.5},{"t":"2026-04-03T00:00:00.000Z","temp":24.1,"humidity":59.2,"aqi":153.5},{"t":"2026-04-03T06:00:00.000Z","temp":29.6,"humidity":41,"aqi":239.3},{"t":"2026-04-03T12:00:00.000Z","temp":24.8,"humidity":55,"aqi":341.3},{"t":"2026-04-03T18:00:00.000Z","temp":22,"humidity":76,"aqi":381.8},{"t":"2026-04-04T00:00:00.000Z","temp":23.6,"humidity":68.5,"aqi":282.3},{"t":"2026-04-04T06:00:00.000Z","temp":27.9,"humidity":44.5,"aqi":158.7},{"t":"2026-04-04T12:00:00.000Z","temp":24.4,"humidity":66.7,"aqi":131.7},{"t":"2026-04-04T18:00:00.000Z","temp":21.5,"humidity":70.7,"aqi":140},{"t":"2026-04-05T00:00:00.000Z","temp":22.2,"humidity":68.7,"aqi":152.2},{"t":"2026-04-05T06:00:00.000Z","temp":28.7,"humidity":31.7,"aqi":153.3},{"t":"2026-04-05T12:00:00.000Z","temp":24.5,"humidity":64,"aqi":153},{"t":"2026-04-05T18:00:00.000Z","temp":22.4,"humidity":49.3,"aqi":166.3},{"t":"2026-04-06T00:00:00.000Z","temp":24.5,"humidity":49.2,"aqi":195.8},{"t":"2026-04-06T06:00:00.000Z","temp":31.1,"humidity":20,"aqi":199.3},{"t":"2026-04-06T12:00:00.000Z","temp":25.9,"humidity":36.2,"aqi":198.2},{"t":"2026-04-06T18:00:00.000Z","temp":22.9,"humidity":48,"aqi":193.5},{"t":"2026-04-07T00:00:00.000Z","temp":23.8,"humidity":48.2,"aqi":193.3},{"t":"2026-04-07T06:00:00.000Z","temp":25.5,"humidity":46.2,"aqi":273.2},{"t":"2026-04-07T12:00:00.000Z","temp":19.8,"humidity":75.8,"aqi":355.8},{"t":"2026-04-07T18:00:00.000Z","temp":17.5,"humidity":90.7,"aqi":327.5},{"t":"2026-04-08T00:00:00.000Z","temp":18.8,"humidity":83.3,"aqi":237.3},{"t":"2026-04-08T06:00:00.000Z","temp":24.8,"humidity":51.2,"aqi":168.2},{"t":"2026-04-08T12:00:00.000Z","temp":20.3,"humidity":68.2,"aqi":139.3},{"t":"2026-04-08T18:00:00.000Z","temp":18,"humidity":85.2,"aqi":125.2},{"t":"2026-04-09T00:00:00.000Z","temp":19.3,"humidity":84.2,"aqi":122},{"t":"2026-04-09T06:00:00.000Z","temp":27.9,"humidity":29.7,"aqi":128.2},{"t":"2026-04-09T12:00:00.000Z","temp":24.7,"humidity":48.7,"aqi":144.2},{"t":"2026-04-09T18:00:00.000Z","temp":19.4,"humidity":64.3,"aqi":144},{"t":"2026-04-10T00:00:00.000Z","temp":20.9,"humidity":58.8,"aqi":167.8},{"t":"2026-04-10T06:00:00.000Z","temp":30.1,"humidity":24.8,"aqi":291.7},{"t":"2026-04-10T12:00:00.000Z","temp":28,"humidity":25.5,"aqi":565.3},{"t":"2026-04-10T18:00:00.000Z","temp":24,"humidity":40.2,"aqi":725.5},{"t":"2026-04-11T00:00:00.000Z","temp":24.7,"humidity":43.2,"aqi":767.7},{"t":"2026-04-11T06:00:00.000Z","temp":32.3,"humidity":22.5,"aqi":732.3},{"t":"2026-04-11T12:00:00.000Z","temp":29.1,"humidity":28,"aqi":543.3},{"t":"2026-04-11T18:00:00.000Z","temp":25.2,"humidity":40.2,"aqi":414.8},{"t":"2026-04-12T00:00:00.000Z","temp":26,"humidity":43.2,"aqi":346.8},{"t":"2026-04-12T06:00:00.000Z","temp":33.5,"humidity":19.2,"aqi":299.3},{"t":"2026-04-12T12:00:00.000Z","temp":30.2,"humidity":20.5,"aqi":384},{"t":"2026-04-12T18:00:00.000Z","temp":24.4,"humidity":34.5,"aqi":463.3},{"t":"2026-04-13T00:00:00.000Z","temp":25.1,"humidity":42.2,"aqi":453.7},{"t":"2026-04-13T06:00:00.000Z","temp":33.7,"humidity":17.5,"aqi":432.7},{"t":"2026-04-13T12:00:00.000Z","temp":31.3,"humidity":17.3,"aqi":377.5},{"t":"2026-04-13T18:00:00.000Z","temp":24.6,"humidity":35.3,"aqi":302.5},{"t":"2026-04-14T00:00:00.000Z","temp":27.6,"humidity":34.8,"aqi":289.3},{"t":"2026-04-14T06:00:00.000Z","temp":36.8,"humidity":13.3,"aqi":235.7},{"t":"2026-04-14T12:00:00.000Z","temp":33.4,"humidity":17.5,"aqi":183.8},{"t":"2026-04-14T18:00:00.000Z","temp":26.4,"humidity":30.5,"aqi":173.2},{"t":"2026-04-15T00:00:00.000Z","temp":28.2,"humidity":32,"aqi":154.8},{"t":"2026-04-15T06:00:00.000Z","temp":38,"humidity":10.7,"aqi":161},{"t":"2026-04-15T12:00:00.000Z","temp":34.2,"humidity":14.3,"aqi":180.7},{"t":"2026-04-15T18:00:00.000Z","temp":27.5,"humidity":28,"aqi":207.8},{"t":"2026-04-16T00:00:00.000Z","temp":30.5,"humidity":28.8,"aqi":311},{"t":"2026-04-16T06:00:00.000Z","temp":39.1,"humidity":10.7,"aqi":295.3},{"t":"2026-04-16T12:00:00.000Z","temp":34.8,"humidity":17.8,"aqi":200.7},{"t":"2026-04-16T18:00:00.000Z","temp":28.5,"humidity":29.7,"aqi":152.2},{"t":"2026-04-17T00:00:00.000Z","temp":31.6,"humidity":25,"aqi":130},{"t":"2026-04-17T06:00:00.000Z","temp":39.2,"humidity":12.7,"aqi":149.3},{"t":"2026-04-17T12:00:00.000Z","temp":31.2,"humidity":29.8,"aqi":180.3},{"t":"2026-04-17T18:00:00.000Z","temp":26.8,"humidity":41.8,"aqi":152.7},{"t":"2026-04-18T00:00:00.000Z","temp":28.7,"humidity":44,"aqi":163.5},{"t":"2026-04-18T06:00:00.000Z","temp":39.2,"humidity":15.5,"aqi":183.7},{"t":"2026-04-18T12:00:00.000Z","temp":35.4,"humidity":17,"aqi":195.5},{"t":"2026-04-18T18:00:00.000Z","temp":29.1,"humidity":27.8,"aqi":196.3},{"t":"2026-04-19T00:00:00.000Z","temp":30.6,"humidity":33.7,"aqi":185.7},{"t":"2026-04-19T06:00:00.000Z","temp":39.4,"humidity":12,"aqi":171.5},{"t":"2026-04-19T12:00:00.000Z","temp":35.3,"humidity":14.3,"aqi":170.5},{"t":"2026-04-19T18:00:00.000Z","temp":28.8,"humidity":28,"aqi":203.8},{"t":"2026-04-20T00:00:00.000Z","temp":30.4,"humidity":34,"aqi":283.3},{"t":"2026-04-20T06:00:00.000Z","temp":38.8,"humidity":11.8,"aqi":335},{"t":"2026-04-20T12:00:00.000Z","temp":34.2,"humidity":14.8,"aqi":413.8},{"t":"2026-04-20T18:00:00.000Z","temp":28.1,"humidity":17.7,"aqi":481.5},{"t":"2026-04-21T00:00:00.000Z","temp":29.9,"humidity":22,"aqi":476.2},{"t":"2026-04-21T06:00:00.000Z","temp":38.2,"humidity":13.2,"aqi":459},{"t":"2026-04-21T12:00:00.000Z","temp":34.8,"humidity":17.3,"aqi":467.8},{"t":"2026-04-21T18:00:00.000Z","temp":28.8,"humidity":28.8,"aqi":451.8},{"t":"2026-04-22T00:00:00.000Z","temp":29.9,"humidity":28.8,"aqi":452.7},{"t":"2026-04-22T06:00:00.000Z","temp":39.6,"humidity":11.7,"aqi":444.2},{"t":"2026-04-22T12:00:00.000Z","temp":35.7,"humidity":16,"aqi":417},{"t":"2026-04-22T18:00:00.000Z","temp":29.2,"humidity":25.3,"aqi":378},{"t":"2026-04-23T00:00:00.000Z","temp":31.3,"humidity":17.5,"aqi":356},{"t":"2026-04-23T06:00:00.000Z","temp":40.3,"humidity":11.5,"aqi":350.5},{"t":"2026-04-23T12:00:00.000Z","temp":35.9,"humidity":17,"aqi":274.2},{"t":"2026-04-23T18:00:00.000Z","temp":29.5,"humidity":29.2,"aqi":187.3},{"t":"2026-04-24T00:00:00.000Z","temp":31.7,"humidity":28.3,"aqi":161},{"t":"2026-04-24T06:00:00.000Z","temp":41.3,"humidity":13.5,"aqi":150.8},{"t":"2026-04-24T12:00:00.000Z","temp":36.8,"humidity":18.7,"aqi":158.2},{"t":"2026-04-24T18:00:00.000Z","temp":30.7,"humidity":30.7,"aqi":188.5},{"t":"2026-04-25T00:00:00.000Z","temp":32.9,"humidity":31,"aqi":297},{"t":"2026-04-25T06:00:00.000Z","temp":41.7,"humidity":12.8,"aqi":381},{"t":"2026-04-25T12:00:00.000Z","temp":37.3,"humidity":16.8,"aqi":495.8},{"t":"2026-04-25T18:00:00.000Z","temp":31.5,"humidity":29.3,"aqi":573.7},{"t":"2026-04-26T00:00:00.000Z","temp":32.7,"humidity":30.8,"aqi":560.8},{"t":"2026-04-26T06:00:00.000Z","temp":40.5,"humidity":16.7,"aqi":571.8},{"t":"2026-04-26T12:00:00.000Z","temp":37.3,"humidity":17.5,"aqi":565.8},{"t":"2026-04-26T18:00:00.000Z","temp":30.6,"humidity":30.7,"aqi":564.2},{"t":"2026-04-27T00:00:00.000Z","temp":33.3,"humidity":25.2,"aqi":558.2},{"t":"2026-04-27T06:00:00.000Z","temp":41.4,"humidity":14,"aqi":499.2},{"t":"2026-04-27T12:00:00.000Z","temp":37.2,"humidity":17.7,"aqi":480.2},{"t":"2026-04-27T18:00:00.000Z","temp":31.1,"humidity":32.7,"aqi":538.7},{"t":"2026-04-28T00:00:00.000Z","temp":32.3,"humidity":34.7,"aqi":608.7},{"t":"2026-04-28T06:00:00.000Z","temp":36.4,"humidity":25.3,"aqi":731.8},{"t":"2026-04-28T12:00:00.000Z","temp":32.9,"humidity":34,"aqi":668.2},{"t":"2026-04-28T18:00:00.000Z","temp":30.5,"humidity":47,"aqi":525}]}
